animageo/__init__.py
animageo/__main__.py
animageo/animageo.py
animageo/code.py
animageo/geo/__init__.py
animageo/geo/construction.py
animageo/geo/lib_commands.py
animageo/geo/lib_elements.py
animageo/geo/lib_vars.py
animageo/parsers/__init__.py
animageo/parsers/ggb_generator.py
animageo/parsers/ggb_parser.py
animageo/parsers/short_parser.py
animageo/parsers/svg_parser.py
animageo-0.1.11.dist-info/licenses/LICENSE.txt
geodynamic/__init__.py
geodynamic/__main__.py
geodynamic/manim_dynamic.py
geodynamic/geo/__init__.py
geodynamic/geo/construction.py
geodynamic/geo/lib_commands.py
geodynamic/geo/lib_elements.py
geodynamic/geo/lib_vars.py
geodynamic/parsers/__init__.py
geodynamic/parsers/ggb_generator.py
geodynamic/parsers/ggb_parser.py
geodynamic/parsers/short_parser.py
geodynamic/parsers/svg_parser.py
animageo-0.1.11.dist-info/METADATA
animageo-0.1.11.dist-info/WHEEL
animageo-0.1.11.dist-info/entry_points.txt
animageo-0.1.11.dist-info/top_level.txt
animageo-0.1.11.dist-info/RECORD
