Metadata-Version: 2.4
Name: animageo
Version: 0.1.11
Summary: Tools for using GeoGebra construction, processing with Manim animation and exporting to SVG and MP4
Home-page: http://animageo.ru/
Author: ivaleo
Author-email: ivaleo <ivaleotion@gmail.com>
License: MIT
Project-URL: Homepage, http://animageo.ru/
Keywords: geometry,dynamic,geogebra,manim,animation,drawing,svg,mp4,python
Classifier: Programming Language :: Python :: 3.13
Classifier: Operating System :: OS Independent
Requires-Python: >=3.9
License-File: LICENSE.txt
Requires-Dist: requests>=2.25.1
Requires-Dist: numpy>=1.26.0
Requires-Dist: manim>=0.19.0
Requires-Dist: pycairo>=1.0.0
Requires-Dist: lark>=1.1.5
Provides-Extra: dev
Requires-Dist: build>=1.0.0; extra == "dev"
Requires-Dist: twine>=4.0.0; extra == "dev"
Requires-Dist: setuptools>=65.0.0; extra == "dev"
Dynamic: author
Dynamic: home-page
Dynamic: license-file
Dynamic: requires-python
